api_bridge/__init__.py
api_bridge/cli.py
api_bridge/core.py
smart_api_bridge-0.1.4.dist-info/licenses/LICENSE
smart_api_bridge-0.1.4.dist-info/METADATA
smart_api_bridge-0.1.4.dist-info/WHEEL
smart_api_bridge-0.1.4.dist-info/top_level.txt
smart_api_bridge-0.1.4.dist-info/RECORD
